{
  "md_main_mission_story_1_1": "Ça alors ! Tu as réussi à obtenir\n\u000e\u0002\u0003\u0004\u0000촁 styles de dodo dans\nton Dododex ? Bien joué !",
  "md_main_mission_story_1_2": "Pendant ce temps, j'ai fait des\ndécouvertes sur \u000e\u0000\u0003\u0004毿Ｗle renforcement\ndes Pokémon\u000e\u0000\u0003\u0004\u0000＀.",
  "md_main_mission_story_1_3": "Nous le savions déjà, mais dans\ncette région, \u000e\u0000\u0003\u0004毿Ｗles Pokémon\nse renforcent en dormant\u000e\u0000\u0003\u0004\u0000＀.",
  "md_main_mission_story_1_4": "Cela dit, ils deviennent aussi\nplus forts grâce aux \u000e\u0000\u0003\u0004毿ＷBonbons\u000e\u0000\u0003\u0004\u0000＀ et\naux \u000e\u0000\u0003\u0004毿ＷFragments de Rêve\u000e\u0000\u0003\u0004\u0000＀ !",
  "md_main_mission_story_1_5": "Tu peux par exemple renforcer\nPikachu avec des \u000e\u0000\u0003\u0004毿ＷBonbons Pikachu\u000e\u0000\u0003\u0004\u0000＀\net des \u000e\u0000\u0003\u0004毿ＷFragments de Rêve\u000e\u0000\u0003\u0004\u0000＀.",
  "md_main_mission_story_1_6": "Renforce tes Pokémon de soutien,\nça t'aidera à atteindre ton nouvel\nobjectif : \u000e\u0000\u0003\u0004毿Ｗ\u000e\u0002\u0003\u0004\u0000촁\u000e\u0000\u0003\u0004\u0000＀ styles de dodo !",
  "md_main_mission_story_1_7": "De mon côté, je vais continuer de\ncreuser pour faire \u000e\u0000\u0003\u0004毿Ｗd'autres\ndécouvertes\u000e\u0000\u0003\u0004\u0000＀ comme celle-ci !",
  "md_main_mission_story_1_8": "Poursuivons les recherches sur le\nsommeil avec entrain !",
  "md_main_mission_story_2_1": "Ça alors ! Tu as réussi à obtenir\n\u000e\u0002\u0003\u0004\u0000촁 styles de dodo dans\nton Dododex ? Bien joué !",
  "md_main_mission_story_2_2": "Je n'ai pas flâné non plus ! J'ai\nfait des préparatifs pour que tu\npuisses \u000e\u0000\u0003\u0004毿Ｗcuisiner\u000e\u0000\u0003\u0004\u0000＀ !",
  "md_main_mission_story_2_3": "Jusqu'à présent, Motisma et sa\n\u000e\u0000\u0003\u0004毿Ｗcuisine automatique\u000e\u0000\u0003\u0004\u0000＀ t'ont été\nutiles, je suppose ?",
  "md_main_mission_story_2_4": "Je t'offre donc des ustensiles de\nqualité ! Tu pourras en plus\n\u000e\u0000\u0003\u0004毿Ｗchoisir\u000e\u0000\u0003\u0004\u0000＀ toi-même tes ingrédients !",
  "md_main_mission_story_2_5": "En les combinant, tu devrais\npouvoir préparer des mets pour\nmonter la puissance de Ronflex.",
  "md_main_mission_story_2_6": "Essaie de nouveaux mélanges pour\natteindre ton prochain objectif :\n\u000e\u0000\u0003\u0004毿Ｗ\u000e\u0002\u0003\u0004\u0000촁\u000e\u0000\u0003\u0004\u0000＀ styles de dodo !",
  "md_main_mission_story_2_7": "Pendant ce temps, je vais essayer\nde trouver un accès à une \u000e\u0000\u0003\u0004毿Ｗnouvelle\nzone de recherche\u000e\u0000\u0003\u0004\u0000＀.",
  "md_main_mission_story_2_8": "Poursuivons les recherches sur le\nsommeil avec entrain !",
  "md_main_mission_story_3_1": "Ça alors ! Tu as réussi à obtenir\n\u000e\u0002\u0003\u0004\u0000촁 styles de dodo dans\nton Dododex ? Bien joué !",
  "md_main_mission_story_3_2": "Pendant que tu progressais dans\ntes recherches, je ne suis pas\nresté les bras ballants.",
  "md_main_mission_story_3_3": "J'ai terminé les préparatifs pour\nnous installer dans \u000e\u0000\u0003\u0004毿Ｗune nouvelle\nzone : la Plage Cyan\u000e\u0000\u0003\u0004\u0000＀ !",
  "md_main_mission_story_3_4": "C'est une longue plage de sable\nensoleillée qui baigne dans une\natmosphère chaleureuse.",
  "md_main_mission_story_3_5": "Tu y croiseras sûrement de\nnouveaux Pokémon de \u000e\u0000\u0003\u0004毿Ｗtype Eau\u000e\u0000\u0003\u0004\u0000＀ !",
  "md_main_mission_story_3_6": "Je te conseille vivement d'y aller\npour atteindre ton prochain\nobjectif : \u000e\u0000\u0003\u0004毿Ｗ\u000e\u0002\u0003\u0004\u0000촁\u000e\u0000\u0003\u0004\u0000＀ styles de dodo !",
  "md_main_mission_story_3_7": "Pendant ce temps, je vais trouver\nde \u000e\u0000\u0003\u0004毿Ｗnouveaux moyens\u000e\u0000\u0003\u0004\u0000＀ de t'aider\ndans ta quête !",
  "md_main_mission_story_3_8": "Poursuivons les recherches sur le\nsommeil avec entrain !",
  "md_main_mission_story_4_1": "Ça alors ! Tu as réussi à obtenir\n\u000e\u0002\u0003\u0004\u0000촁 styles de dodo dans\nton Dododex ? Bien joué !",
  "md_main_mission_story_4_2": "De mon côté, j'ai découvert\ncomment faire pour \u000e\u0000\u0003\u0004毿Ｗagrandir\nla taille de ta casserole\u000e\u0000\u0003\u0004\u0000＀.",
  "md_main_mission_story_4_3": "Tu as dû remarquer que tu es\nlimité par le nombre d'ingrédients\nque tu peux utiliser.",
  "md_main_mission_story_4_4": "Eh bien sache que les \u000e\u0000\u0003\u0004毿ＷFragments\nde Rêve\u000e\u0000\u0003\u0004\u0000＀ vont te permettre de\n\u000e\u0000\u0003\u0004毿Ｗrepousser cette limite\u000e\u0000\u0003\u0004\u0000＀ !",
  "md_main_mission_story_4_5": "Grâce à ça, tu pourras préparer\nles plats qui nécessitent \u000e\u0000\u0003\u0004毿Ｗun grand\nnombre d'ingrédients\u000e\u0000\u0003\u0004\u0000＀.",
  "md_main_mission_story_4_6": "Alors agrandis ta casserole pour\natteindre ton prochain objectif :\n\u000e\u0000\u0003\u0004毿Ｗ\u000e\u0002\u0003\u0004\u0000촁\u000e\u0000\u0003\u0004\u0000＀ styles de dodo !",
  "md_main_mission_story_4_7": "Pendant ce temps, je pars à la\ndécouverte d'une \u000e\u0000\u0003\u0004毿Ｗnouvelle zone\u000e\u0000\u0003\u0004\u0000＀ !",
  "md_main_mission_story_4_8": "Poursuivons les recherches sur le\nsommeil avec entrain !",
  "md_main_mission_story_5_1": "Ça alors ! Tu as réussi à obtenir\n\u000e\u0002\u0003\u0004\u0000촁 styles de dodo dans\nton Dododex ? Bien joué !",
  "md_main_mission_story_5_2": "De mon côté, j'ai découvert une\n\u000e\u0000\u0003\u0004毿Ｗnouvelle zone\u000e\u0000\u0003\u0004\u0000＀ !",
  "md_main_mission_story_5_3": "C'est la \u000e\u0000\u0003\u0004毿ＷGrotte Sépia\u000e\u0000\u0003\u0004\u0000＀. Tu peux\nt'y rendre quand tu veux pour tes\nfutures recherches !",
  "md_main_mission_story_5_4": "La lumière qui traverse le trou\ndans la voûte donne une ambiance\nmystique à cette caverne.",
  "md_main_mission_story_5_5": "Tu y trouveras sans doute de\nnouveaux Pokémon de\u000e\u0000\u0003\u0004毿Ｗ types Sol\u000e\u0000\u0003\u0004\u0000＀\net \u000e\u0000\u0003\u0004毿ＷRoche\u000e\u0000\u0003\u0004\u0000＀.",
  "md_main_mission_story_5_6": "Va donc y jeter un œil pour\natteindre ton prochain objectif :\n\u000e\u0000\u0003\u0004毿Ｗ\u000e\u0002\u0003\u0004\u0000촁\u000e\u0000\u0003\u0004\u0000＀ styles de dodo !",
  "md_main_mission_story_5_7": "Pendant que tu explores, je vais\ntrouver de \u000e\u0000\u0003\u0004毿Ｗnouveaux moyens\u000e\u0000\u0003\u0004\u0000＀ de\nt'aider dans ta progression !",
  "md_main_mission_story_5_8": "Poursuivons les recherches sur le\nsommeil avec entrain !",
  "md_main_mission_story_6_1": "Ça alors ! Tu as réussi à obtenir\n\u000e\u0002\u0003\u0004\u0000촁 styles de dodo dans\nton Dododex ? Bien joué !",
  "md_main_mission_story_6_2": "Tu as bien mérité une récompense\nadéquate. La voici !\nC'est une \u000e\u0000\u0003\u0004毿ＷPierre Foudre\u000e\u0000\u0003\u0004\u0000＀ !",
  "md_main_mission_story_6_3": "Comme tu le sais, l'apparence des\nPokémon et leurs stats changent\nénormément après évolution.",
  "md_main_mission_story_6_4": "Et cette dernière peut être\nprovoquée par des objets comme\ncette \u000e\u0000\u0003\u0004毿ＷPierre Foudre\u000e\u0000\u0003\u0004\u0000＀ !",
  "md_main_mission_story_6_5": "Cela dit, les Pokémon n'évoluent\npas uniquement grâce aux objets.\nIl existe différentes méthodes.",
  "md_main_mission_story_6_6": "Fais donc évoluer tes Pokémon de\nsoutien pour atteindre l'objectif\nsuivant : \u000e\u0000\u0003\u0004毿Ｗ\u000e\u0002\u0003\u0004\u0000촁\u000e\u0000\u0003\u0004\u0000＀ styles de dodo !",
  "md_main_mission_story_6_7": "Pendant ce temps, je vais me\ncharger de trouver une \u000e\u0000\u0003\u0004毿Ｗnouvelle\nzone\u000e\u0000\u0003\u0004\u0000＀.",
  "md_main_mission_story_6_8": "Poursuivons les recherches sur le\nsommeil avec entrain !",
  "md_main_mission_story_7_1": "Ça alors ! Tu as réussi à obtenir\n\u000e\u0002\u0003\u0004\u0000촁 styles de dodo dans\nton Dododex ? Bien joué !",
  "md_main_mission_story_7_2": "Tu te souviens de la \u000e\u0000\u0003\u0004毿Ｗnouvelle zone\u000e\u0000\u0003\u0004\u0000＀\ndont je t'ai parlé la dernière\nfois ?",
  "md_main_mission_story_7_3": "Je l'ai trouvée, et elle est prête à\nt'accueillir !\nC'est la \u000e\u0000\u0003\u0004毿ＷPlaine Perce-neige\u000e\u0000\u0003\u0004\u0000＀ !",
  "md_main_mission_story_7_4": "Il s'agit d'un endroit silencieux\noù la neige tombe en permanence.",
  "md_main_mission_story_7_5": "Elle abrite pas mal de nouveaux\nPokémon de \u000e\u0000\u0003\u0004毿Ｗtype Glace\u000e\u0000\u0003\u0004\u0000＀.",
  "md_main_mission_story_7_6": "N'hésite pas à t'y rendre pour\natteindre ton prochain objectif :\n\u000e\u0000\u0003\u0004毿Ｗ\u000e\u0002\u0003\u0004\u0000촁\u000e\u0000\u0003\u0004\u0000＀ styles de dodo !",
  "md_main_mission_story_7_7": "Je vais en profiter pour continuer\nà chercher de \u000e\u0000\u0003\u0004毿Ｗnouvelles manières\u000e\u0000\u0003\u0004\u0000＀\nde t'aider dans ton travail !",
  "md_main_mission_story_7_8": "Poursuivons les recherches sur le\nsommeil avec entrain !",
  "md_main_mission_story_8_1": "Ça alors ! Tu as réussi à obtenir\n\u000e\u0002\u0003\u0004\u0000촁 styles de dodo dans\nton Dododex ? Bien joué !",
  "md_main_mission_story_8_2": "J'ai un \u000e\u0000\u0003\u0004毿ＷTicket de Camping\u000e\u0000\u0003\u0004\u0000＀ pour te\nrécompenser de tous tes efforts !",
  "md_main_mission_story_8_3": "Il te sera très utile pour élever\n\u000e\u0000\u0003\u0004毿ＷRonflex\u000e\u0000\u0003\u0004\u0000＀ et progresser dans tes\n\u000e\u0000\u0003\u0004毿Ｗrecherches sur le sommeil\u000e\u0000\u0003\u0004\u0000＀.",
  "md_main_mission_story_8_4": "Il va te permettre de louer un\nKit de Camping pendant \u000e\u0000\u0003\u0004毿Ｗsept\u000e\u0000\u0003\u0004\u0000＀\n\u000e\u0000\u0003\u0004毿Ｗjours\u000e\u0000\u0003\u0004\u0000＀ et qui aura deux effets.",
  "md_main_mission_story_8_5": "\u000e\u0000\u0003\u0004毿ＷUn Pokémon en plus\u000e\u0000\u0003\u0004\u0000＀ apparaîtra\nquand tu dors, et tes Pokémon de\nsoutien \u000e\u0000\u0003\u0004毿Ｗagiront plus vite\u000e\u0000\u0003\u0004\u0000＀ !",
  "md_main_mission_story_8_6": "Essaie-le donc pour remplir ton\nprochain objectif :\n\u000e\u0000\u0003\u0004毿Ｗ\u000e\u0002\u0003\u0004\u0000촁\u000e\u0000\u0003\u0004\u0000＀ styles de dodo !",
  "md_main_mission_story_8_7": "Pendant ce temps, je m'en vais\npréparer une \u000e\u0000\u0003\u0004毿Ｗnouvelle zone\u000e\u0000\u0003\u0004\u0000＀ !",
  "md_main_mission_story_8_8": "Poursuivons les recherches sur le\nsommeil avec entrain !",
  "md_main_mission_story_13_1": "Ça alors ! Tu as réussi à obtenir\n\u000e\u0002\u0003\u0004\u0000촁 styles de dodo dans\nton Dododex ? Bien joué !",
  "md_main_mission_story_13_2": "Réjouis-toi, car tu vas pouvoir\nexplorer une \u000e\u0000\u0003\u0004毿Ｗnouvelle zone\u000e\u0000\u0003\u0004\u0000＀ !",
  "md_main_mission_story_13_3": "J'ai tout préparé pour que tu\npuisses te rendre sur le \u000e\u0000\u0003\u0004毿ＷRivage\u000e\u0000\u0003\u0004\u0000＀\n\u000e\u0000\u0003\u0004毿ＷLapis-lazuli\u000e\u0000\u0003\u0004\u0000＀ !",
  "md_main_mission_story_13_4": "C'est un lieu reposant où nos\noreilles sont bercées par le bruit\ndes vagues sur le rivage.",
  "md_main_mission_story_13_5": "Tu devrais y rencontrer de\nnouveaux Pokémon de \u000e\u0000\u0003\u0004毿Ｗtype\u000e\u0000\u0003\u0004\u0000＀\n\u000e\u0000\u0003\u0004毿ＷDragon\u000e\u0000\u0003\u0004\u0000＀.",
  "md_main_mission_story_13_6": "Rend visite à cet endroit pour\natteindre ton prochain objectif :\n\u000e\u0000\u0003\u0004毿Ｗ\u000e\u0002\u0003\u0004\u0000촁\u000e\u0000\u0003\u0004\u0000＀ styles de dodo !",
  "md_main_mission_story_13_7": "Pendant ce temps, je vais me\ncharger de trouver un \u000e\u0000\u0003\u0004毿Ｗnouvel\u000e\u0000\u0003\u0004\u0000＀\n\u000e\u0000\u0003\u0004毿Ｗobjet\u000e\u0000\u0003\u0004\u0000＀ utile à ta quête.",
  "md_main_mission_story_13_8": "Poursuivons les recherches sur le\nsommeil avec entrain !",
  "md_main_mission_story_14_1": "Ça alors ! Tu as réussi à obtenir\n\u000e\u0002\u0003\u0004\u0000촁 styles de dodo dans\nton Dododex ? Bien joué !",
  "md_main_mission_story_14_2": "Tu mérites sans le moindre doute\nde recevoir cette \u000e\u0000\u0003\u0004毿ＷGraine de\nCompétence Secondaire \u000e\u0000\u0003\u0004\u0000＀!",
  "md_main_mission_story_14_3": "Tu l'as sans doute remarqué, mais\nchacun de tes Pokémon possède\ndes \u000e\u0000\u0003\u0004毿Ｗcompétences secondaires\u000e\u0000\u0003\u0004\u0000＀. ",
  "md_main_mission_story_14_4": "Cette graine permet de \u000e\u0000\u0003\u0004毿Ｗfaire\u000e\u0000\u0003\u0004\u0000＀\n\u000e\u0000\u0003\u0004毿Ｗmonter la qualité de l'une de ces\u000e\u0000\u0003\u0004\u0000＀\n\u000e\u0000\u0003\u0004毿Ｗcompétences aléatoirement\u000e\u0000\u0003\u0004\u0000＀.",
  "md_main_mission_story_14_5": "Cela aura pour effet d'améliorer\nsoudainement l'effet de cette\ncompétence secondaire.",
  "md_main_mission_story_14_6": "Utilise-la sur un Pokémon de\nsoutien pour atteindre l'objectif\nsuivant : \u000e\u0000\u0003\u0004毿Ｗ\u000e\u0002\u0003\u0004\u0000촁\u000e\u0000\u0003\u0004\u0000＀ styles de dodo !",
  "md_main_mission_story_14_7": "Pendant ce temps, je continue\nmes études pour faire d'autres\n\u000e\u0000\u0003\u0004毿Ｗdécouvertes utiles\u000e\u0000\u0003\u0004\u0000＀ !",
  "md_main_mission_story_14_8": "Poursuivons les recherches sur le\nsommeil avec entrain !",
  "md_main_mission_story_waiting_update": "Je t'offre un petit quelque chose\npour t'aider dans tes futurs\nobjectifs de Dododex !"
}