{
  "ShopSceneController_Text_3": "ダイヤ不足",
  "ShopSceneController_Text_4": "ダイヤが不足しています",
  "ShopSceneController_Text_7": "購入完了",
  "ShopSceneController_Text_8": "購入完了しました",
  "ShopSceneController_Text_9": "購入状況の復元",
  "ShopSceneController_Text_10": "購入時のエラーに対する復元処理を行います\n\nサーバー通信を行って購入状況を復元しますか？",
  "ShopSceneController_Text_19": "復元成功",
  "ShopSceneController_Text_11": "購入エラーを復元しました",
  "ShopSceneController_Text_12": "ダイヤ不足",
  "ShopSceneController_Text_13": "ダイヤが不足しているため\n購入ができませんでした",
  "ShopSceneController_Text_14": "販売期間外アイテム",
  "ShopSceneController_Text_15": "販売期間を過ぎているため\n購入ができませんでした",
  "ShopSceneController_Text_16": "以前の購入にエラーは見つかりませんでした",
  "ShopSceneController_Text_17": "購入失敗",
  "ShopSceneController_Text_18": "今月の購入上限をオーバーしました\n月が変わりましたら、再度お試しください",
  "ShopConsumableItemCell_Text_1": "\u000e\u0002\u0002\u0002\u0000個",
  "ShopConsumableItemCell_Text_1_DiaVer": "\u000e\u0002\u0003\u0004\u0000촁個",
  "ShopScene_Content_Title": "総合ショップ",
  "ShopScene_Content_Desc": "各種アイテムやダイヤを購入することができます",
  "ShopScene_Content_Title_2": "期間限定パック：あと\u000e\u0002\u0001\u0002\u0000日",
  "ShopScene_Content_Title_2_0day": "期間限定パック：あと\u000e\u0002\u0001\u0002\u0000時間",
  "ShopScene_Content_Title_2_0hour": "期間限定パック：あと\u000e\u0002\u0001\u0002\u0000分",
  "ShopScene_Content_Messasge": "\u000e\u0002\u0001\u0002\u0000個限定",
  "ShopScene_Content_Messasge_Soldout": "売り切れ",
  "ShopScene_Content_Price_Dia": "\u000e\u0002\u0003\u0004\u0000촁",
  "ShopScene_Content_Title_3": "お得なパック - 更新まであと\u000e\u0002\u0001\u0002\u0000日",
  "ShopScene_Content_Title_3_0day": "お得なパック - 更新まであと\u000e\u0002\u0001\u0002\u0000時間",
  "ShopScene_Content_Title_3_0hour": "お得なパック - 更新まであと\u000e\u0002\u0001\u0002\u0000分",
  "ShopScene_Content_Message": "お得なパックを\n購入すると\nゆめのかたまりMが\n毎月各3個まで\nオマケでもらえます",
  "ShopScene_Content_Messasge_2": "あと\u000e\u0002\u0001\u0002\u0000回",
  "ShopScene_Content_Messasge_4": "オマケなし",
  "ShopScene_Content_Messasge_3": "\u000e\u0003\u0003\u0004Ā촀",
  "ShopScene_Content_Title_4": "どうぐ",
  "ShopScene_Content_Title_5": "アップグレード",
  "ShopScene_Content_UpgradeName_1": "ポケモン\nボックス拡張",
  "ShopScene_Content_UpgradeName_2": "食材バッグ\n拡張",
  "ShopScene_Content_UpgradeName_3": "どうぐバッグ\n拡張",
  "ShopScene_Content_BagUpgradePopup_Title": "バッグ拡張",
  "ShopScene_Content_BagUpgradePopup_Text": "ダイヤ\u000e\u0002\u0004\u0004\u0000촁個を消費して\n最大容量を\u000e\u0002\u0002\u0002\u0001増やしますか？",
  "ShopScene_Content_BoxUpgradePopup_Title": "ボックス拡張",
  "ShopScene_Content_BoxUpgradePopup_Text": "ダイヤ\u000e\u0002\u0004\u0004\u0000촁個を消費して\n最大容量を\u000e\u0002\u0002\u0002\u0001増やしますか？",
  "ShopScene_Content_BagUpgradePopup_Success_Text": "最大容量が\u000e\u0002\u0002\u0002\u0000増えました",
  "ShopScene_Content_BoxUpgradePopup_Success_Text": "ポケモンボックスの\n最大容量が\u000e\u0002\u0002\u0002\u0000増えました",
  "ShopScene_Content_Title_6": "ダイヤ",
  "ShopScene_Content_Name_3": "ダイヤ",
  "ShopScene_Content_Number": "\u000e\u0002\u0001\u0002\u0000個",
  "ShopScene_Content_Name_4": "資金決済法について",
  "ShopScene_Content_Name_5": "特定商取引法について",
  "ShopScene_Content_Name_6": "請約撤回について",
  "ShopScene_Content_Name_7": "購入の復元",
  "ShopScene_Header_Title": "ショップ",
  "ShopScene_Dia_Detail_0": "所持ダイヤ",
  "ShopScene_Dia_Detail_1": "有償ダイヤ：\u000e\u0002\u0007\u0004\u0000촁個\nボーナスダイヤ：\u000e\u0002\u0007\u0004\u0001촁個\n\n※ダイヤは有償分から先に消費されます",
  "ShopScene_Item_Detail_0": "購入する",
  "ShopScene_Item_Detail_1": "所持数 \u000e\u0002\u0006\u0004\u0000촁",
  "ShopScene_Item_Detail_2": "説明",
  "ShopScene_Item_Detail_3": "キャンセル",
  "ShopScene_Item_Detail_4": "\u000e\u0002\u0003\u0004\u0000촁",
  "ShopScene_Item_Detail_5": "所持数",
  "ShopScene_Item_Detail_6": "ダイヤ",
  "ShopScene_Item_Detail_7": "購入しますか？",
  "ShopScene_Item_Detail_8": "\u000e\u0002\u0003\u0004\u0000촁",
  "ShopScene_Item_Detail_9": "\u000e\u0002\u0003\u0004\u0000촁",
  "ShopScene_Item_Detail_10": "\u000e\u0002\t\u0004\u0000촁",
  "ShopScene_Item_Detail_11": "\u000e\u0002\t\u0004\u0000촁",
  "ShopScene_Item_Detail_12": "購入する",
  "ShopScene_Item_Detail_13": "\u000e\u0003\u0003\u0004Ā촀 x\u000e\u0002\u0001\u0002\u0002を\n購入しました",
  "ShopScene_Item_Detail_14": "オマケつき あと\u000e\u0002\u0000\u0002촀個",
  "ShopScene_Item_Detail_23": "限定 あと\u000e\u0002\u0000\u0002촀個",
  "ShopScene_Item_Detail_15": "パック内容",
  "ShopScene_Item_Detail_16": "\u000e\u0003\u0003\u0004Ā촀 x\u000e\u0002\u0002\u0002\u0002",
  "ShopScene_Item_Detail_17": "\u000e\u0003\u0003\u0004Ā촀 x\u000e\u0002\u0002\u0002\u0002 （ オマケ ）",
  "ShopScene_Item_Detail_18": "x\u000e\u0002\u0003\u0004\u0000촁",
  "ShopScene_Item_Detail_22": "+\u000e\u0002\u0002\u0002\u0000",
  "ShopScene_Item_Detail_19": "確認",
  "ShopScene_Item_Detail_20": "完了",
  "ShopScene_Item_Detail_21": "\u000e\u0003\u0003\u0004Ā촀",
  "ShopScene_Dialog_Heading": "内訳",
  "ShopScene_Dialog_Text_1": "ダイヤ ( 有償 ) x\u000e\u0002\u0003\u0004\u0000촁",
  "ShopScene_Dialog_Text_2": "ダイヤ ( ボーナス ) x\u000e\u0002\u0003\u0004\u0000촁",
  "ShopScene_Hub_HeaderTitle": "ショップ",
  "ShopScene_Hub_Title": "ショップ",
  "ShopScene_Hub_Text": "アイテムの購入や交換はこちら",
  "ShopScene_Hub_ShopButton": "総合ショップ",
  "ShopScene_Hub_NormalButton": "ノーマル交換所",
  "ShopScene_Hub_PremiumButton": "プレミアム交換所",
  "ShopScene_Hub_Header": "スリープポイント交換所",
  "ShopScene_Hub_UpdateDate": "更新まで あと\u000e\u0002\u0001\u0002\u0000日",
  "ShopScene_Hub_UpdateDate_0day": "更新まで あと\u000e\u0002\u0001\u0002\u0000時間",
  "ShopScene_Hub_UpdateDate_0hour": "更新まで あと\u000e\u0002\u0001\u0002\u0000分",
  "ShopScene_ShopPopup_Limited_Label": "限定",
  "ShopScene_ShopPopup_Limited_LeftNum": "あと\u000e\u0002\u0001\u0002\u0000個",
  "ShopScene_ShopPopup_Limited_Soldout": "売り切れ",
  "ShopScene_ShopPopup_Pack_Label": "オマケつき",
  "ShopScene_ShopPopup_Pack_Label_Soldout": "オマケ売り切れ",
  "ShopScene_ShopPopup_Pack_Bonus_Desc": "お得なパックを購入すると「\u000e\u0003\u0003\u0004Ā촀」を\n毎月各\u000e\u0002\u0001\u0002\u0002個までオマケでもらえます",
  "ShopScene_ShopPopup_BaitBall_Title": "ポケサブレ",
  "ShopScene_ShopPopup_BaitBall_Cell_ItemName": "\u000e\u0003\u0003\u0004Ā촀 \u000e\u0000\u0003\u0004香ﾙx\u000e\u0000\u0003\u0004\u0000＀ \u000e\u0002\u0002\u0002\u0002",
  "ShopScene_ShopPopup_PurchasePopup_Title": "ダイヤ購入",
  "ShopScene_ShopPopup_Tab_DiamondShop": "ダイヤ",
  "ShopScene_ShopPopup_Tab_SleepPointShop": "スリープポイント",
  "ShopScene_ShopPopup_PurchaseCell_ItemName_1": "ダイヤ",
  "ShopScene_ShopPopup_PurchaseCell_ItemName_2": "ダイヤ",
  "ShopScene_ShopPopup_PurchaseCell_ItemName_3": "ダイヤ",
  "ShopScene_ShopPopup_PurchaseCell_ItemName_4": "ダイヤ",
  "ShopScene_ShopPopup_PurchaseCell_ItemName_5": "ダイヤ",
  "ShopScene_ShopPopup_PurchaseCell_ItemName_6": "ダイヤ",
  "ShopScene_ShopPopup_PurchasePopupCell_ItemName": "ダイヤ \u000e\u0000\u0003\u0004香ﾙx\u000e\u0000\u0003\u0004\u0000＀ \u000e\u0002\u0004\u0004\u0000촁",
  "ShopScene_ShopPopup_PurchasePopupCell_Desc_NoBonus": "有償ダイヤ \u000e\u0002\u0004\u0004\u0000촁",
  "ShopScene_ShopPopup_PurchasePopupCell_Desc_WithBonus": "有償ダイヤ \u000e\u0002\u0004\u0004\u0000촁\n+ ボーナスダイヤ \u000e\u0002\u0004\u0004\u0001촁",
  "ShopScene_ShopPopup_DiaAlreadyMaxPopup_Title": "有償ダイヤの所持上限",
  "ShopScene_ShopPopup_DiaAlreadyMaxPopup_Text": "有償ダイヤの所持上限は50,000個です\n上限を超えてしまう購入はできません",
  "ShopScene_ShopPopup_ItemAlreadyMaxPopup_Title": "アイテムの所持上限",
  "ShopScene_ShopPopup_ItemAlreadyMaxPopup_Text_1": "このアイテムの所持上限を超えてしまうため\n購入できません",
  "ShopScene_ShopPopup_ItemAlreadyMaxPopup_Text_2": "パックのアイテムのうち、\n所持上限を超えてしまうものがあるため\n購入できません",
  "ShopScene_ShopPopup_BagAlreadyMaxPopup_Title": "バッグの上限",
  "ShopScene_ShopPopup_BagAlreadyMaxPopup_Text": "どうぐバッグがいっぱいなため\n購入できません\nどうぐバッグを整理してください",
  "ShopScene_ShopPopup_StoreRefund_Title": "重要なお知らせ",
  "ShopScene_ShopPopup_StoreRefund_Text_Apple": "AppStoreで返金処理が行われた商品があります。\n該当する商品を回収させていただきました。\n\nストア：AppStore\nアイテム名：\u000e\u0003\u0012\u0002촀\n購入日時：\u000e\t\u0000$ yyyy/MM/dd_hh:mm\u0001\n返金日時：\u000e\t\u0000$ yyyy/MM/dd_hh:mm\u0002",
  "ShopScene_ShopPopup_StoreRefund_Text_Google": "GooglePlayで返金処理が行われた商品があります。\n該当する商品を回収させていただきました。\n\nストア：GooglePlay\nアイテム名：\u000e\u0003\u0012\u0002촀\n購入日時：\u000e\t\u0000$ yyyy/MM/dd_hh:mm\u0001\n返金日時：\u000e\t\u0000$ yyyy/MM/dd_hh:mm\u0002"
}